naoth/__init__.py
naoth/constants.py
naoth/spl.py
naoth/datasets/__init__.py
naoth/datasets/edgels.py
naoth/datasets/fsr.py
naoth/datasets/images.py
naoth/datasets/joints.py
naoth/datasets/motion.py
naoth/log/__init__.py
naoth/log/_experimental_parser.py
naoth/log/_experimental_reader.py
naoth/log/_experimental_xabsl.py
naoth/log/_hdf5.py
naoth/log/_parser.py
naoth/log/_reader.py
naoth/log/_xabsl.py
naoth/log/utils.py
naoth/math/__init__.py
naoth/math/_math2d.py
naoth/math/_math3d.py
naoth/pb/AudioData_pb2.py
naoth/pb/CommonTypes_pb2.py
naoth/pb/Framework_Representations_pb2.py
naoth/pb/Messages_pb2.py
naoth/pb/Representations_pb2.py
naoth/pb/RobotPose_pb2.py
naoth/pb/TeamMessage_pb2.py
naoth/pb/__init__.py
naoth/utils/DebugProxy.py
naoth/utils/__init__.py
naoth/utils/_camera.py
naoth/utils/_debug.py
naoth/utils/_image.py
naoth-0.5.1.dist-info/METADATA
naoth-0.5.1.dist-info/WHEEL
naoth-0.5.1.dist-info/top_level.txt
naoth-0.5.1.dist-info/RECORD
