Metadata-Version: 2.1
Name: naoth
Version: 0.5.1
Summary: Python utils for the NaoTH toolchain
Home-page: UNKNOWN
Author: NaoTH Berlin United
Author-email: nao-team@informatik.hu-berlin.de
License: Apache License 2.0
Platform: UNKNOWN
Requires-Python: >=3.6.9
Requires-Dist: numpy
Requires-Dist: protobuf (==3.20.3)
